request_sentinal/__init__.py
request_sentinal/exceptions.py
request_sentinal/logger.py
request_sentinal/processor.py
request_sentinal/proxy_manager.py
request_sentinal/robots_checker.py
request_sentinal/utils.py
request_sentinal/algorithms/__init__.py
request_sentinal/algorithms/fixed_window.py
request_sentinal/algorithms/leaky_bucket.py
request_sentinal/algorithms/sliding_window.py
request_sentinal/algorithms/token_bucket.py
request_sentinal-1.2.0.dist-info/LICENSE
request_sentinal-1.2.0.dist-info/METADATA
request_sentinal-1.2.0.dist-info/WHEEL
request_sentinal-1.2.0.dist-info/top_level.txt
request_sentinal-1.2.0.dist-info/RECORD
